[
  {
    "id": 1,
    "name": "Computer Science",
    "logo": "/assets/fist.png",
    "activities": [
      {
        "text": "Won 1st Prize in National Hackathon 2024",
        "image": "/assets/activites/cse1.jpeg"
      },
      {
        "text": "Published 10 research papers in 2023",
        "image": "/assets/research-papers.png"
      },
      {
        "text": "Internship MoU with Infosys",
        "image": "/assets/infosys-mou.png"
      }
    ]
  },
  {
    "id": 2,
    "name": "Civil Engineering",
    "logo": "/assets/civil.png",
    "activities": [
      {
        "text": "Designed eco-friendly vehicle prototype",
        "image": "/assets/eco-vehicle.png"
      },
      {
        "text": "MoU with Desometric Engineering Services",
        "image": "/assets/desometric-mou.png"
      }
    ]
  },
  {
    "id": 3,
    "name": "Electronics and Communication Engineering",
    "logo": "/assets/ece.png",
    "activities": [
      {
        "text": "Developed smart grid system",
        "image": "/assets/smart-grid.png"
      }
    ]
  },
  {
    "id": 4,
    "name": "Electrical and Electronics Engineering",
    "logo": "/assets/eee.png",
    "activities": [
      {
        "text": "Built sustainable bridge model",
        "image": "/assets/bridge-model.png"
      }
    ]
  },
  {
    "id": 5,
    "name": "Artificial Intelligence and Data Science",
    "logo": "/assets/ai.png",
    "activities": [
      {
        "text": "Innovated bio-fuel production",
        "image": "/assets/bio-fuel.png"
      }
    ]
  },
  {
    "id": 6,
    "name": "Information Technology",
    "logo": "/assets/it.jpg",
    "activities": [
      {
        "text": "Designed drone prototype",
        "image": "/assets/drone-prototype.png"
      }
    ]
  },
  {
    "id": 7,
    "name": "Mechanical Engineering",
    "logo": "/assets/mech.png",
    "activities": [
      {
        "text": "Developed new enzyme for medical use",
        "image": "/assets/enzyme-medical.png"
      }
    ]
  }
]